viz_tokens_component/__init__.py
viz_tokens_component/frontend/build/asset-manifest.json
viz_tokens_component/frontend/build/bootstrap.min.css
viz_tokens_component/frontend/build/index.html
viz_tokens_component/frontend/build/precache-manifest.849ec3e56e8895b5eff7683f7815bdad.js
viz_tokens_component/frontend/build/precache-manifest.c0f9a1dd46d6298b4acf6b328674d36c.js
viz_tokens_component/frontend/build/service-worker.js
viz_tokens_component/frontend/build/static/js/2.1f7660f1.chunk.js
viz_tokens_component/frontend/build/static/js/2.1f7660f1.chunk.js.LICENSE.txt
viz_tokens_component/frontend/build/static/js/2.1f7660f1.chunk.js.map
viz_tokens_component/frontend/build/static/js/main.00b97b63.chunk.js
viz_tokens_component/frontend/build/static/js/main.00b97b63.chunk.js.map
viz_tokens_component/frontend/build/static/js/main.2552536f.chunk.js
viz_tokens_component/frontend/build/static/js/main.2552536f.chunk.js.map
viz_tokens_component/frontend/build/static/js/runtime-main.d58b2606.js
viz_tokens_component/frontend/build/static/js/runtime-main.d58b2606.js.map
st_tokenization_vis_component-0.0.8.dist-info/LICENSE
st_tokenization_vis_component-0.0.8.dist-info/METADATA
st_tokenization_vis_component-0.0.8.dist-info/WHEEL
st_tokenization_vis_component-0.0.8.dist-info/top_level.txt
st_tokenization_vis_component-0.0.8.dist-info/RECORD
